{
  "transcripts": [
    {
      "confidence": -129.42430114746094,
      "date": "2021-07-15",
      "time": "09.00",
      "filename": "cbs88_8-2021-07-15_T09.00.01.mp3137.wav",
      "radio_station": "cbs88_8",
      "words": [
        {
          "word": "abafa",
          "start_time": 0.08,
          "duration": 0.28
        },
        {
          "word": "ekirwadde",
          "start_time": 0.4,
          "duration": 0.36
        },
        {
          "word": "kya",
          "start_time": 0.8,
          "duration": 0.14
        },
        {
          "word": "covid",
          "start_time": 0.98,
          "duration": 0.3
        },
        {
          "word": "okweyongera",
          "start_time": 1.36,
          "duration": 2.36
        },
        {
          "word": "omuggalo",
          "start_time": 3.92,
          "duration": 0.44
        },
        {
          "word": "gulangiddwa",
          "start_time": 4.42,
          "duration": 0.72
        },
        {
          "word": "gwa",
          "start_time": 5.18,
          "duration": 0.12
        },
        {
          "word": "kusinga",
          "start_time": 5.32,
          "duration": 0.34
        },
        {
          "word": "mu",
          "start_time": 5.7,
          "duration": 0.08
        },
        {
          "word": "kibuga",
          "start_time": 5.8,
          "duration": 0.3
        },
        {
          "word": "ekikulu",
          "start_time": 6.12,
          "duration": 0.38
        },
        {
          "word": "kigali",
          "start_time": 6.54,
          "duration": 0.7
        },
        {
          "word": "ne",
          "start_time": 7.3,
          "duration": 0.12
        },
        {
          "word": "district",
          "start_time": 7.44,
          "duration": 0.36
        },
        {
          "word": "endala",
          "start_time": 7.86,
          "duration": 0.2
        },
        {
          "word": "munaana",
          "start_time": 8.1,
          "duration": 0.36
        },
        {
          "word": "ezeetoolodde",
          "start_time": 8.5,
          "duration": 0.6
        },
        {
          "word": "ekibuga",
          "start_time": 9.14,
          "duration": 0.36
        }
      ]
    }
  ]
}