{"transcripts": [{"confidence": -206.69346618652344, "date": "2021-06-22", "time": "19.00", "filename": "cbs89_2-2021-06-22_T19.00.011.mp3096.wav", "radio_station": "cbs89_2", "words": [{"word": "nalongo", "start_time": 0.04, "duration": 0.46}, {"word": "kalumba", "start_time": 0.54, "duration": 0.56}, {"word": "mateeka", "start_time": 1.16, "duration": 0.8}, {"word": "taata", "start_time": 2.0, "duration": 0.34}, {"word": "we", "start_time": 2.36, "duration": 0.26}, {"word": "yagenze", "start_time": 2.64, "duration": 0.56}, {"word": "ekiro", "start_time": 3.4, "duration": 1.02}, {"word": "tubasabidde", "start_time": 4.46, "duration": 0.84}, {"word": "ko", "start_time": 5.32, "duration": 0.1}, {"word": "munnamwe", "start_time": 5.48, "duration": 1.48}, {"word": "ku", "start_time": 7.0, "duration": 0.14}, {"word": "kirwadde", "start_time": 7.16, "duration": 0.36}, {"word": "kino", "start_time": 7.56, "duration": 0.22}, {"word": "e", "start_time": 7.82, "duration": 0.04}, {"word": "acid", "start_time": 7.98, "duration": 0.62}, {"word": "booka", "start_time": 8.82, "duration": 1.06}], "url": "https://firebasestorage.googleapis.com/v0/b/nlp-audio-store.appspot.com/o/audios%2Fcbs89_2-2021-06-22_T19.00.011.mp3096.wav?alt=media&token=5945a0b0-cdd2-4982-a377-0b116f2c6f3e"}]}